csiroct_imbl_asci/__init__.py
csiroct_imbl_asci/convert.py
csiroct_imbl_asci/version.py
csiroct_imbl_asci/xtract.py
csiroct_imbl_asci-0.1.7.dist-info/LICENSE
csiroct_imbl_asci-0.1.7.dist-info/METADATA
csiroct_imbl_asci-0.1.7.dist-info/WHEEL
csiroct_imbl_asci-0.1.7.dist-info/top_level.txt
csiroct_imbl_asci-0.1.7.dist-info/RECORD
